.gitignore
.pre-commit-config.yaml
.readthedocs.yaml
LICENSE
MANIFEST.in
README.md
create_distortion.py
create_quartic_fit_coeffs.py
create_synthetic_psf.py
example.png
example_config.toml
pyproject.toml
.github/workflows/ci.yaml
.github/workflows/ci_fixed.yaml
.github/workflows/python-publish.yaml
docs/Makefile
docs/make.bat
docs/source/conf.py
docs/source/index.rst
docs/source/_static/favicon.ico
docs/source/_static/logo.png
simpunch/__init__.py
simpunch/cli.py
simpunch/flow.py
simpunch/level0.py
simpunch/level1.py
simpunch/level2.py
simpunch/level3.py
simpunch/noise.py
simpunch/spike.py
simpunch/stars.py
simpunch/util.py
simpunch.egg-info/PKG-INFO
simpunch.egg-info/SOURCES.txt
simpunch.egg-info/dependency_links.txt
simpunch.egg-info/entry_points.txt
simpunch.egg-info/requires.txt
simpunch.egg-info/top_level.txt
simpunch/data/distortion_NFI.fits
simpunch/data/distortion_WFI.fits
simpunch/data/trefoil_mask.npz
simpunch/data/hit_maps/CRMAP_HI1_M01_S50_E00_A0000_I1.hmp
simpunch/data/hit_maps/CRMAP_HI1_M01_S50_E00_A0000_I2.hmp
simpunch/data/hit_maps/CRMAP_HI1_M01_S50_E00_A0000_I3.hmp
simpunch/data/hit_maps/CRMAP_HI1_M01_S50_E00_A0000_I4.hmp
simpunch/data/hit_maps/CRMAP_HI1_M01_S50_E00_A0000_I5.hmp
simpunch/data/hit_maps/CRMAP_HI1_M01_S50_E00_A0000_I6.hmp
simpunch/data/hit_maps/CRMAP_HI1_M01_S50_E00_A0000_I7.hmp
simpunch/data/hit_maps/CRMAP_HI1_M01_S50_E00_A0000_I8.hmp
simpunch/tests/__init__.py
simpunch/tests/test_distortion.py
simpunch/tests/test_noise.py
simpunch/tests/test_spike.py
simpunch/tests/test_starfield.py