Metadata-Version: 2.1
Name: simpunch
Version: 0.0.3
Summary: Simulate PUNCH observations
Author-email: "J. Marcus Hughes" <hughes.jmb@gmail.com>, Chris Lowder <chris.lowder@swri.org>
Maintainer-email: "J. Marcus Hughes" <hughes.jmb@gmail.com>
Project-URL: Documentation, https://punch-mission.github.io/simpunch/
Project-URL: Repository, https://github.com/punch-mission/simpunch.git
Project-URL: Bug Tracker, https://github.com/punch-mission/simpunch/issues
Project-URL: Changelog, https://github.com/punch-mission/simpunch/blob/main/CHANGELOG.md
Keywords: PUNCH,NASA,simulate,data,solar physics
Classifier: Development Status :: 4 - Beta
Classifier: Programming Language :: Python
Requires-Python: >=3.10
License-File: LICENSE
Requires-Dist: numpy
Requires-Dist: astropy
Requires-Dist: pandas
Requires-Dist: matplotlib
Requires-Dist: regularizepsf
Requires-Dist: prefect[dask,sqlalchemy]
Requires-Dist: punchbowl
Requires-Dist: toml
Requires-Dist: scipy
Requires-Dist: photutils
Provides-Extra: test
Requires-Dist: pytest; extra == "test"
Requires-Dist: pytest-doctestplus; extra == "test"
Requires-Dist: pytest-cov; extra == "test"
Requires-Dist: ruff; extra == "test"
Requires-Dist: coverage; extra == "test"
Provides-Extra: docs
Requires-Dist: sphinx; extra == "docs"
Requires-Dist: sphinx-autoapi; extra == "docs"
Requires-Dist: sphinx-automodapi; extra == "docs"
Requires-Dist: pydata-sphinx-theme; extra == "docs"
Requires-Dist: sphinx-favicon; extra == "docs"
Requires-Dist: ipython; extra == "docs"
Requires-Dist: packaging; extra == "docs"
